pytale/__init__.py
pytale/pytale.py
pytale-0.1.3.dist-info/METADATA
pytale-0.1.3.dist-info/WHEEL
pytale-0.1.3.dist-info/top_level.txt
pytale-0.1.3.dist-info/RECORD
